{
    "name": "Static Site with Firebase",
    "image": "mcr.microsoft.com/devcontainers/javascript-node:18",
    "features": {
      "ghcr.io/devcontainers/features/github-cli:1": {}
    },
    "customizations": {
      "vscode": {
        "extensions": [
          "ms-azuretools.vscode-azurestaticwebapps",
          "dbaeumer.vscode-eslint",
          "esbenp.prettier-vscode",
          "ritwickdey.liveserver"
        ]
      }
    },
    "forwardPorts": [5000, 5001, 8080],
    "postCreateCommand": "npm install -g firebase-tools live-server",
    "remoteUser": "node"
  }